wow_ai_mms/__init__.py
wow_ai_mms/_logger.py
wow_ai_mms/constants.py
wow_ai_mms/examples/mms/MODEL_CARD.md
wow_ai_mms/examples/mms/README.md
wow_ai_mms/examples/mms/asr/config/infer_common.yaml
wow_ai_mms/examples/mms/asr/infer/example_infer_adapter.sh
wow_ai_mms/examples/mms/asr/infer/mms_infer.py
wow_ai_mms/examples/mms/data_prep/README.md
wow_ai_mms/examples/mms/data_prep/align_and_segment.py
wow_ai_mms/examples/mms/data_prep/align_utils.py
wow_ai_mms/examples/mms/data_prep/norm_config.py
wow_ai_mms/examples/mms/data_prep/punctuations.lst
wow_ai_mms/examples/mms/data_prep/sox/.git/HEAD
wow_ai_mms/examples/mms/data_prep/sox/.git/config
wow_ai_mms/examples/mms/data_prep/sox/.git/description
wow_ai_mms/examples/mms/data_prep/sox/.git/hooks/applypatch-msg.sample
wow_ai_mms/examples/mms/data_prep/sox/.git/hooks/commit-msg.sample
wow_ai_mms/examples/mms/data_prep/sox/.git/hooks/fsmonitor-watchman.sample
wow_ai_mms/examples/mms/data_prep/sox/.git/hooks/post-update.sample
wow_ai_mms/examples/mms/data_prep/sox/.git/hooks/pre-applypatch.sample
wow_ai_mms/examples/mms/data_prep/sox/.git/hooks/pre-commit.sample
wow_ai_mms/examples/mms/data_prep/sox/.git/hooks/pre-merge-commit.sample
wow_ai_mms/examples/mms/data_prep/sox/.git/hooks/pre-push.sample
wow_ai_mms/examples/mms/data_prep/sox/.git/hooks/pre-rebase.sample
wow_ai_mms/examples/mms/data_prep/sox/.git/hooks/pre-receive.sample
wow_ai_mms/examples/mms/data_prep/sox/.git/hooks/prepare-commit-msg.sample
wow_ai_mms/examples/mms/data_prep/sox/.git/hooks/push-to-checkout.sample
wow_ai_mms/examples/mms/data_prep/sox/.git/hooks/update.sample
wow_ai_mms/examples/mms/data_prep/sox/.git/index
wow_ai_mms/examples/mms/data_prep/sox/.git/info/exclude
wow_ai_mms/examples/mms/data_prep/sox/.git/logs/HEAD
wow_ai_mms/examples/mms/data_prep/sox/.git/logs/refs/heads/master
wow_ai_mms/examples/mms/data_prep/sox/.git/logs/refs/remotes/origin/HEAD
wow_ai_mms-0.2.0.dist-info/LICENSE
wow_ai_mms-0.2.0.dist-info/METADATA
wow_ai_mms-0.2.0.dist-info/WHEEL
wow_ai_mms-0.2.0.dist-info/RECORD
